pandas_validator/__init__.py
pandas_validator/core.py
pandas_validator/io_utils.py
pandas_datavalidation-1.0.0.dist-info/METADATA
pandas_datavalidation-1.0.0.dist-info/WHEEL
pandas_datavalidation-1.0.0.dist-info/top_level.txt
pandas_datavalidation-1.0.0.dist-info/RECORD
