Metadata-Version: 2.4
Name: pandas_datavalidation
Version: 1.0.0
Summary: A simple survey data validation package using pandas.
Home-page: https://github.com/ChandraCherupally/pandas_validator
Author: NaveenChandra Cherupally
Author-email: cherupallynaveen@gmail.com
Requires-Python: >=3.8
Requires-Dist: pandas>=2.3.3
Requires-Dist: numpy>=2.2.6
Requires-Dist: pyreadstat==1.3.1
Dynamic: author
Dynamic: author-email
Dynamic: description
Dynamic: description-content-type
Dynamic: home-page
Dynamic: requires-dist
Dynamic: requires-python
Dynamic: summary
